<annotation>
	<folder>data</folder>
	<filename>car0477.jpg</filename>
	<path>/home/hanxy/icra/data/car0477.jpg</path>
	<source>
		<database>Unknown</database>
	</source>
	<size>
		<width>640</width>
		<height>480</height>
		<depth>3</depth>
	</size>
	<segmented>0</segmented>
	<object>
		<name>car</name>
		<pose>Unspecified</pose>
		<truncated>0</truncated>
		<difficult>0</difficult>
		<bndbox>
			<xmin>182</xmin>
			<ymin>178</ymin>
			<xmax>452</xmax>
			<ymax>419</ymax>
		</bndbox>
	</object>
	<object>
		<name>armer</name>
		<pose>Unspecified</pose>
		<truncated>0</truncated>
		<difficult>0</difficult>
		<bndbox>
			<xmin>312</xmin>
			<ymin>320</ymin>
			<xmax>397</xmax>
			<ymax>395</ymax>
		</bndbox>
	</object>
</annotation>
