<annotation>
	<folder>data</folder>
	<filename>car1875.jpg</filename>
	<path>/home/hanxy/icra/data/car1875.jpg</path>
	<source>
		<database>Unknown</database>
	</source>
	<size>
		<width>640</width>
		<height>480</height>
		<depth>3</depth>
	</size>
	<segmented>0</segmented>
	<object>
		<name>car</name>
		<pose>Unspecified</pose>
		<truncated>0</truncated>
		<difficult>0</difficult>
		<bndbox>
			<xmin>150</xmin>
			<ymin>35</ymin>
			<xmax>369</xmax>
			<ymax>236</ymax>
		</bndbox>
	</object>
	<object>
		<name>armer</name>
		<pose>Unspecified</pose>
		<truncated>0</truncated>
		<difficult>0</difficult>
		<bndbox>
			<xmin>215</xmin>
			<ymin>151</ymin>
			<xmax>277</xmax>
			<ymax>207</ymax>
		</bndbox>
	</object>
</annotation>
