<annotation>
	<folder>data</folder>
	<filename>car33133.jpg</filename>
	<path>/home/hanxy/icra/data/car33133.jpg</path>
	<source>
		<database>Unknown</database>
	</source>
	<size>
		<width>640</width>
		<height>480</height>
		<depth>3</depth>
	</size>
	<segmented>0</segmented>
	<object>
		<name>car</name>
		<pose>Unspecified</pose>
		<truncated>0</truncated>
		<difficult>0</difficult>
		<bndbox>
			<xmin>132</xmin>
			<ymin>56</ymin>
			<xmax>436</xmax>
			<ymax>352</ymax>
		</bndbox>
	</object>
	<object>
		<name>armer</name>
		<pose>Unspecified</pose>
		<truncated>0</truncated>
		<difficult>0</difficult>
		<bndbox>
			<xmin>274</xmin>
			<ymin>238</ymin>
			<xmax>371</xmax>
			<ymax>318</ymax>
		</bndbox>
	</object>
	<object>
		<name>wheel</name>
		<pose>Unspecified</pose>
		<truncated>0</truncated>
		<difficult>0</difficult>
		<bndbox>
			<xmin>387</xmin>
			<ymin>231</ymin>
			<xmax>432</xmax>
			<ymax>326</ymax>
		</bndbox>
	</object>
	<object>
		<name>wheel</name>
		<pose>Unspecified</pose>
		<truncated>0</truncated>
		<difficult>0</difficult>
		<bndbox>
			<xmin>171</xmin>
			<ymin>251</ymin>
			<xmax>213</xmax>
			<ymax>346</ymax>
		</bndbox>
	</object>
	<object>
		<name>wheel</name>
		<pose>Unspecified</pose>
		<truncated>0</truncated>
		<difficult>0</difficult>
		<bndbox>
			<xmin>135</xmin>
			<ymin>205</ymin>
			<xmax>164</xmax>
			<ymax>289</ymax>
		</bndbox>
	</object>
	<object>
		<name>armer</name>
		<pose>Unspecified</pose>
		<truncated>0</truncated>
		<difficult>0</difficult>
		<bndbox>
			<xmin>153</xmin>
			<ymin>212</ymin>
			<xmax>186</xmax>
			<ymax>292</ymax>
		</bndbox>
	</object>
</annotation>
